paraphrase_metrics/__init__.py
paraphrase_metrics/metrics.py
paraphrase_metrics-0.0.1.dist-info/LICENSE
paraphrase_metrics-0.0.1.dist-info/METADATA
paraphrase_metrics-0.0.1.dist-info/WHEEL
paraphrase_metrics-0.0.1.dist-info/top_level.txt
paraphrase_metrics-0.0.1.dist-info/RECORD
